odoo/addons/rental_pricelist_interval/README.rst
odoo/addons/rental_pricelist_interval/__init__.py
odoo/addons/rental_pricelist_interval/__manifest__.py
odoo/addons/rental_pricelist_interval/hooks.py
odoo/addons/rental_pricelist_interval/README/CONFIGURATION.rst
odoo/addons/rental_pricelist_interval/README/CONTRIBUTORS.rst
odoo/addons/rental_pricelist_interval/README/DESCRIPTION.rst
odoo/addons/rental_pricelist_interval/README/HISTORY.rst
odoo/addons/rental_pricelist_interval/README/USAGE.rst
odoo/addons/rental_pricelist_interval/data/product_pricelist_data.xml
odoo/addons/rental_pricelist_interval/data/product_uom_data.xml
odoo/addons/rental_pricelist_interval/i18n/de.po
odoo/addons/rental_pricelist_interval/i18n/rental_pricelist_interval.pot
odoo/addons/rental_pricelist_interval/migrations/12.0.1.0.2/post-set-interval-pricelist.py
odoo/addons/rental_pricelist_interval/migrations/12.0.1.0.3/post-add-interval-service-and-pricelist-item.py
odoo/addons/rental_pricelist_interval/models/__init__.py
odoo/addons/rental_pricelist_interval/models/product.py
odoo/addons/rental_pricelist_interval/models/res_company.py
odoo/addons/rental_pricelist_interval/models/sale.py
odoo/addons/rental_pricelist_interval/security/ir.model.access.csv
odoo/addons/rental_pricelist_interval/static/description/icon.png
odoo/addons/rental_pricelist_interval/static/description/index.html
odoo/addons/rental_pricelist_interval/tests/__init__.py
odoo/addons/rental_pricelist_interval/tests/test_rental_pricelist.py
odoo/addons/rental_pricelist_interval/views/product_view.xml
odoo/addons/rental_pricelist_interval/views/res_company_view.xml
odoo/addons/rental_pricelist_interval/views/sale_view.xml
odoo12_addon_rental_pricelist_interval-12.0.1.0.4.dist-info/METADATA
odoo12_addon_rental_pricelist_interval-12.0.1.0.4.dist-info/WHEEL
odoo12_addon_rental_pricelist_interval-12.0.1.0.4.dist-info/top_level.txt
odoo12_addon_rental_pricelist_interval-12.0.1.0.4.dist-info/RECORD
